daily_py/__init__.py
daily_py/collections.py
daily_py/files.py
daily_py_fun-1.0.0.dist-info/METADATA
daily_py_fun-1.0.0.dist-info/WHEEL
daily_py_fun-1.0.0.dist-info/top_level.txt
daily_py_fun-1.0.0.dist-info/RECORD
